{
  "warnings_id": 401,
  "faults_id": 402,
  "warnings_counts_id": 403,
  "faults_counts_id": 404,
  "warnings": {
    "TractiveSystemOvercurrent": {
      "id": 101,
      "description": "Tractive system overcurrent detected (<-265A or >70.8A)."
    },
    "MissingVCHeartbeat": {
      "id": 115,
      "description": "Missing heartbeat from the VC."
    },
    "CriticalPrechargeFailure": {
      "id": 451,
      "description": "Precharge failed >3x"
    }
  },
  "faults": {
    "IMDFault": {
      "id": 201,
      "description": "Insulation monitoring device fault detected."
    },
    "AMSFault": {
      "id": 202,
      "description": "AMS fault detected."
    },
    "BSPDFault": {
      "id": 203,
      "description": "BSPD fault detected."
    }
  },
  "info_id": 405,
  "info_counts_id": 406,
  "info": {
    "StackOverflow": {
      "id": 450,
      "description": "An RTOS task stack overflowed on the previous boot cycle."
    }
  }
}
